LICENSE.txt
MANIFEST.in
README.md
setup.py
doc/Makefile
doc/acknowledgments.rst
doc/authors.rst
doc/conf.py
doc/index.rst
doc/install.rst
doc/make.bat
doc/modules.rst
doc/release_notes.rst
doc/bib/viziphant.bib
doc/images/viziphant_favicon.ico
doc/images/viziphant_logo.png
doc/images/viziphant_logo_sidebar.png
requirements/requirements-docs.txt
requirements/requirements-tests.txt
requirements/requirements.txt
viziphant/VERSION
viziphant/__init__.py
viziphant/asset.py
viziphant/events.py
viziphant/gpfa.py
viziphant/patterns.py
viziphant/rasterplot.py
viziphant/spike_train_correlation.py
viziphant/spike_train_synchrony.py
viziphant/statistics.py
viziphant/unitary_event_analysis.py
viziphant/utils.py
viziphant.egg-info/PKG-INFO
viziphant.egg-info/SOURCES.txt
viziphant.egg-info/dependency_links.txt
viziphant.egg-info/requires.txt
viziphant.egg-info/top_level.txt
viziphant/patterns_src/__init__.py
viziphant/patterns_src/hypergraph.py
viziphant/patterns_src/view.py
viziphant/test/test_asset.py