Metadata-Version: 2.1
Name: viziphant
Version: 0.4.0
Summary: Viziphant is a package for the visualization of the analysisresults of electrophysiology data in Python
Home-page: https://github.com/INM-6/viziphant
Author: Viziphant authors and contributors
Author-email: contact@python-elephant.org
License: BSD
Classifier: Development Status :: 5 - Production/Stable
Classifier: Intended Audience :: Science/Research
Classifier: License :: OSI Approved :: BSD License
Classifier: Natural Language :: English
Classifier: Operating System :: OS Independent
Classifier: Programming Language :: Python :: 2
Classifier: Programming Language :: Python :: 3
Classifier: Topic :: Scientific/Engineering
License-File: LICENSE.txt
Requires-Dist: neo>=0.9.0
Requires-Dist: elephant>=0.9.0
Requires-Dist: numpy>=1.19.5
Requires-Dist: quantities>=0.14.1
Requires-Dist: matplotlib>=3.3.2
Requires-Dist: seaborn>=0.9.0
Requires-Dist: bokeh>=3.0.0
Requires-Dist: holoviews>=1.16.0
Requires-Dist: networkx>=3.0.0
